{"doc":["365","306","28","25","11","13","xz","show","dk","ddy","51modo","rosi","disi","ishow","pan","vgirl","ru1mm","sityl","show","dk","ddy","51modo","rosi","disi","ishow","pan","vgirl","ru1mm","sityl","cosplai","2129","show","dk","ddy","51modo","rosi","disi","ishow","pan","vgirl","ru1mm","sityl","show","dk","ddy","51modo","rosi","disi","ishow","pan","vgirl","ru1mm","sityl","cosplai","xz","xiaoyu","vol","561","booti","mtyh","vol","446","jk","mtyh","vol","450","imiss","vol","605","mygirl","vol","550","akasha","xiuren","3651","xiaoyu","vol","562","sugar","xiuren","3652","victoria","xiuren","3654","mia","xiuren","3653","ol","xiuren","3655","sandi","xiuren","3656","arud","yalayi","vol","798","mtyh","vol","451","xiaoyu","vol","563","booti","xiuren","3657","xiuren","3658","allen","imiss","vol","606","lavinia","xiuren","3659","ol","mfstar","vol","511"],"headings":["xz","xz","xz"],"url":"https://0xzn.com","previewTitle":"XZ图片网-做美女套图精品写真,我们是专业的","preview":"XZ图片网是一家有温度的图片站,不仅提供了精品套图、美女套图,偶尔还会分享各种新鲜壁纸、高品质头像图片等,良心就完事了.","forwardLinks":[]}