{"doc":["xxx","video","real","mom","japanes","mom","mom","son","xxx","mom","son","young","teen","step","mom","son","sleep","step","mom","mom","man","young","girl","blond","mom","chines","sister","anal","japanes","indian","mom","japanes","cheat","step","brother","sister","china","dad","granni","anal","anal","gai","granni","japanes","famili","shemal","lesbian","mom","young","girl","bbw","tube","porn","free","tube","video","popular","video","top","rate","video","video","tube","pornstar","tube","tag","tube","channel","wild","521","mom","5738","milf","14758","amateur","21279","matur","5771","teen","14645","big","cock","11312","young","5157","group","sex","1763","cute","1537","arab","904","yoga","325","black","6406","top","819","angri","33","finger","3570","norwegian","wet","2217","home","video","1139","wife","5316","son","2774","stepmom","1261","sex","toi","2458","cumshot","11788","squirt","2005","strang","444","parti","673","lingeri","3224","dp","869","pervert","76","public","2810","lezdom","32","taboo","1197","surpris","265","face","fuck","422","tall","1095","joi","657","censor","1175","south","african","27","barefoot","49","tube","porn","free","tube","video","tube","pornstar","tube","tag","channel","tube","porn","video"],"headings":["free","tube","porn","video","101","tube","porn","hd","porn","tube","video","xxx","porn","movi","beauti","pussi","101tubeporn"],"url":"https://101tubeporn.com","previewTitle":"Free Tube Porn Videos | 101 Tube Porn","preview":"HD Porn Tube Videos, XXX Porn Movies and Beautiful Pussies at 101TubePorn.com","forwardLinks":[]}