{"doc":["2024","18","yo","right","reserv","model","18","asian","teen","live","teen","cam","stream","teen","film","porn","don","18","yo","deutsch","fran","ai","espa","ol","italiano","portugu","rk","home","late","top","rate","view","categori","deutsch","fran","ai","espa","ol","italiano","portugu","rk","view","top","rate","long","favorit","58","close","butt","sex","deep","twerk","meat","perspect","20","hour","48","12","soft","sex","sweet","teeni","17","hour","19","home","fine","lingeri","oral","sex","point","view","hour","25","german","jerk","instruct","spunk","countdown","doggystyl","huge","rear","masturb","hour","26","44","charm","skinni","gf","nylon","sock","hard","nail","bf","hour","10","22","jame","fuck","hole","glass","dildo","22","hour","22","follow","eat","vagina","squirt","mouth","face","64","hour","04","sadmiss","boyfriend","bj","hard","core","orgi","bed","hour","03","bitch","touch","floor","15","100","hour","35","37","youngster","lover","sexi","sock","passion","sex","middl","night","14","hour","27","36","youngster","gf","screw","tight","vagina","classmat","31","hour","23","close","amateur","fine","lip","bj","perspect","10","hour","53","cum","level","9000","fuck","chang","life","alexi","crystal","396","100","hour","17","24","youngster","gf","tight","twat","fuck","bf","wang","31","hour","55","close","deep","mouth","fuck","oral","sex","point","view","14","hour","12","25","colombian","bitch","ask","stop","hold","rod","total","slut","hour","00","close","snatch","fuck","larg","cum","shoot","butthol","perspect","hour","29","20","teen","fuck","hard","hot","sock","gigant","schlong","fill","condom","sperm","53","hour","12","close","sweet","red","lip","swallow","rod","point","view","16","100","hour","58","close","doggystyl","perspect","amateur","film","hour","prev","page","15848","page","view","threesom","3k","84","step","fantasi","21k","85","teen","93k","81","orgi","0k","82","babysitt","6k","82","home","term","dmca","18","2257","video","view","categori"],"headings":["18","yo","free","porn","tube","18","yo","porn","pornpedia","featur","huge","rang","amaz","free","sex","video","amaz","porn","movi","porn","tube","porn","video","free","sex","video","free","porn","tube"],"url":"https://18yos.co","previewTitle":"18 Yos - Free Porn Tube","preview":"18 Yos is a porn pornpedia featuring a huge range of amazing free sex videos and amazing porn movies.","forwardLinks":[]}